inspera/__init__.py
inspera/candidate.py
inspera/cleaner.py
inspera/question.py
inspera/reader.py
InsperaReader-0.1.1.dist-info/LICENSE
InsperaReader-0.1.1.dist-info/METADATA
InsperaReader-0.1.1.dist-info/WHEEL
InsperaReader-0.1.1.dist-info/top_level.txt
InsperaReader-0.1.1.dist-info/RECORD
