Metadata-Version: 2.1
Name: InsperaReader
Version: 0.1.1
Summary: JSON parsing of Inspera Assessment files
Home-page: https://github.com/ph10m/inspera-reader
Author: Tollef Jørgensen
Author-email: tollefj@gmail.com
License: MIT License: http://opensource.org/licenses/MIT
Download-URL: https://github.com/ph10m/inspera-reader
Keywords: JSON,Inspera,parser,dataset
Platform: UNKNOWN
Classifier: Intended Audience :: Science/Research
Classifier: License :: OSI Approved :: MIT License
Classifier: Natural Language :: English
Classifier: Programming Language :: Python :: 3.5
Classifier: Topic :: Scientific/Engineering :: Information Analysis
License-File: LICENSE
